pulumi_authentik/__init__.py
pulumi_authentik/_utilities.py
pulumi_authentik/application.py
pulumi_authentik/application_entitlement.py
pulumi_authentik/blueprint.py
pulumi_authentik/brand.py
pulumi_authentik/certificate_key_pair.py
pulumi_authentik/enterprise_license.py
pulumi_authentik/event_rule.py
pulumi_authentik/event_transport.py
pulumi_authentik/flow.py
pulumi_authentik/flow_stage_binding.py
pulumi_authentik/get_brand.py
pulumi_authentik/get_certificate_key_pair.py
pulumi_authentik/get_flow.py
pulumi_authentik/get_group.py
pulumi_authentik/get_groups.py
pulumi_authentik/get_property_mapping_provider_rac.py
pulumi_authentik/get_property_mapping_provider_radius.py
pulumi_authentik/get_property_mapping_provider_saml.py
pulumi_authentik/get_property_mapping_provider_scim.py
pulumi_authentik/get_property_mapping_provider_scope.py
pulumi_authentik/get_property_mapping_source_ldap.py
pulumi_authentik/get_provider_oauth2_config.py
pulumi_authentik/get_provider_saml_metadata.py
pulumi_authentik/get_rbac_permission.py
pulumi_authentik/get_service_connection_kubernetes.py
pulumi_authentik/get_source.py
pulumi_authentik/get_stage.py
pulumi_authentik/get_user.py
pulumi_authentik/get_users.py
pulumi_authentik/get_webauthn_device_type.py
pulumi_authentik/group.py
pulumi_authentik/outpost.py
pulumi_authentik/outputs.py
pulumi_authentik/policy_binding.py
pulumi_authentik/policy_dummy.py
pulumi_authentik/policy_event_matcher.py
pulumi_authentik/policy_expiry.py
pulumi_authentik/policy_expression.py
pulumi_authentik/policy_geoip.py
pulumi_authentik/policy_password.py
pulumi_authentik/policy_reputation.py
pulumi_authentik/policy_unique_password.py
pulumi_authentik/property_mapping_google_workspace.py
pulumi_authentik/property_mapping_ldap.py
pulumi_authentik/property_mapping_microsoft_entra.py
pulumi_authentik/property_mapping_notification.py
pulumi_authentik/property_mapping_provider_google_workspace.py
pulumi_authentik/property_mapping_provider_microsoft_entra.py
pulumi_authentik-2025.8.1.dist-info/METADATA
pulumi_authentik-2025.8.1.dist-info/WHEEL
pulumi_authentik-2025.8.1.dist-info/top_level.txt
pulumi_authentik-2025.8.1.dist-info/RECORD
