Metadata-Version: 2.4
Name: pulumi_authentik
Version: 2025.8.1
Summary: A Pulumi provider dynamically bridged from authentik.
Project-URL: Repository, https://github.com/goauthentik/terraform-provider-authentik
Requires-Python: >=3.9
Requires-Dist: parver>=0.2.1
Requires-Dist: pulumi<4.0.0,>=3.165.0
Requires-Dist: semver>=2.8.1
Requires-Dist: typing-extensions<5,>=4.11; python_version < "3.11"
